gbmframework/__init__.py
gbmframework/base.py
gbmframework/tuning.py
gbmframework/utils.py
gbmframework/models/__init__.py
gbmframework/models/catboost_model.py
gbmframework/models/lightgbm_model.py
gbmframework/models/xgboost_model.py
gbmframework-0.1.7.dist-info/LICENSE
gbmframework-0.1.7.dist-info/METADATA
gbmframework-0.1.7.dist-info/WHEEL
gbmframework-0.1.7.dist-info/top_level.txt
gbmframework-0.1.7.dist-info/RECORD
